code/cpu/reg_file_module/reg_file.v
`timescale 1ns/100ps

// TODO : write testbench 
module reg_file(IN, OUT1, OUT2, INADDRESS, OUT1ADDRESS, OUT2ADDRESS, WRITE_EN, CLK, RESET);
    
    input [31:0]  IN; // 32 bit data input
    input [4:0] INADDRESS, OUT1ADDRESS, OUT2ADDRESS;  //5bit data inputs
    input WRITE_EN, CLK, RESET;  //1 bit data inputs
    output reg [31:0] OUT1, OUT2; //32 bit data outputs

    reg [31:0]  REGISTERS [31:0]; //32 bit x 32 register reg_file


    // Read on negative clock edge
    always @ (negedge CLK) 
    begin
        OUT1 <= #3 REGISTERS[OUT1ADDRESS];
        OUT2 <= #3 REGISTERS[OUT2ADDRESS];
    end

    // Write on positive clock edge 
    integer i;
    always @ (posedge CLK) 
    begin
        if (RESET == 1'b1)
        begin
            for (i = 0; i < 32; i = i + 1)
            begin
                REGISTERS[i] = 0;       // Write zero to all registers
            end
        end
        else
        begin
            // on paper RAND_INPUT assigned to REG[31]
            // and PC to REG[30] for ISR
            if (WRITE_EN == 1'b1)
            begin
                REGISTERS[INADDRESS] = IN;    
            end
            //TODO : check for interrupt 
        end
    end


endmodule

code/cpu/testbench/reg_file/reg_file_tb.v
`include "../../cpu/reg_file_module/reg_file.v"
`timescale 1ns/100ps

module reg_file_tb;

    // Declare connections to ALU
    reg[31:0] IN;
    reg[4:0] INADDRESS, OUT1ADDRESS, OUT2ADDRESS;
    reg WRITE_EN, CLK, RESET;
    wire[31:0] OUT1, OUT2;

    // Instantiate ALU module
    reg_file my_reg_file(IN, OUT1, OUT2, INADDRESS, OUT1ADDRESS,OUT2ADDRESS, WRITE_EN, CLK, RESET);

    integer i;

    initial begin
        $dumpfile("reg_file_tb.vcd");
        $dumpvars(0,my_reg_file);
        for(i=0;i<31;i=i+1)
            $dumpvars(1, reg_file_tb.my_reg_file.reg_file.REGISTERS[i]);
    end

    initial begin

        CLK = 1'b0;
        RESET = 1'b1;
        WRITE_EN = 1'b0; // write enable not needed for reset
        IN = 32'b00000000000000000000000000000010;
        INADDRESS = 5'b00000;
        OUT1ADDRESS = 5'b00011;
        OUT2ADDRESS = 5'b00001;

        #1;
        CLK = 1'b1;
        RESET = 1'b1;
        WRITE_EN = 1'b0; // write enable not needed for reset
        IN = 32'b00000000000000000000000000000010;
        INADDRESS = 5'b00000;
        OUT1ADDRESS = 5'b00011;
        OUT2ADDRESS = 5'b00001;

        #1;
        CLK = 1'b0;
        RESET = 1'b0;
        WRITE_EN = 1'b0; 
        IN = 32'b00000000000000000000000000000010;
        INADDRESS = 5'b00000;
        OUT1ADDRESS = 5'b00011;
        OUT2ADDRESS = 5'b00001;

        #1;
        CLK = 1'b1;
        RESET = 1'b0;
        WRITE_EN = 1'b1; 
        IN = 32'b00000000000000000000000000000010;
        INADDRESS = 5'b00000;
        OUT1ADDRESS = 5'b00011;
        OUT2ADDRESS = 5'b00001;


        #1
        CLK = 1'b0;
        RESET = 1'b0;
        WRITE_EN = 1'b0; 
        IN = 32'b00000000000000000000000000000010;
        INADDRESS = 5'b00000;
        OUT1ADDRESS = 5'b00010;
        OUT2ADDRESS = 5'b00001;


        #1;
        CLK = 1'b1;
        RESET = 1'b0;
        WRITE_EN = 1'b0; 
        IN = 32'b00000000000000000000000000000010;
        INADDRESS = 5'b00000;
        OUT1ADDRESS = 5'b00000;
        OUT2ADDRESS = 5'b00010;


        #1;
        CLK = 1'b0;
        RESET = 1'b0;
        WRITE_EN = 1'b0; 
        IN = 32'b00000000000000000000000000000010;
        INADDRESS = 5'b00000;
        OUT1ADDRESS = 5'b00000;
        OUT2ADDRESS = 5'b00001;

        #1;
        CLK = 1'b1;
        RESET = 1'b1;
        WRITE_EN = 1'b0; 
        IN = 32'b00000000000000000000000000000010;
        INADDRESS = 5'b00000;
        OUT1ADDRESS = 5'b00000;
        OUT2ADDRESS = 5'b00010;
        #1;


        $finish;

    end

endmodule

code/cpu/testbench/reg_file/reg_file_tb.vcd
$date
	Fri Mar 17 11:14:46 2023
$end
$version
	Icarus Verilog
$end
$timescale
	100ps
$end
$scope module reg_file_tb $end
$scope module my_reg_file $end
$var wire 1 ! CLK $end
$var wire 32 " IN [31:0] $end
$var wire 5 # INADDRESS [4:0] $end
$var wire 32 $ OUT1 [31:0] $end
$var wire 5 % OUT1ADDRESS [4:0] $end
$var wire 32 & OUT2 [31:0] $end
$var wire 5 ' OUT2ADDRESS [4:0] $end
$var wire 1 ( RESET $end
$var wire 1 ) WRITE_EN $end
$var integer 32 * i [31:0] $end
$upscope $end
$upscope $end
$scope module reg_file_tb $end
$scope module my_reg_file $end
$var reg 32 + \REGISTERS[0] [31:0] $end
$upscope $end
$upscope $end
$scope module reg_file_tb $end
$scope module my_reg_file $end
$var reg 32 , \REGISTERS[1] [31:0] $end
$upscope $end
$upscope $end
$scope module reg_file_tb $end
$scope module my_reg_file $end
$var reg 32 - \REGISTERS[2] [31:0] $end
$upscope $end
$upscope $end
$scope module reg_file_tb $end
$scope module my_reg_file $end
$var reg 32 . \REGISTERS[3] [31:0] $end
$upscope $end
$upscope $end
$scope module reg_file_tb $end
$scope module my_reg_file $end
$var reg 32 / \REGISTERS[4] [31:0] $end
$upscope $end
$upscope $end
$scope module reg_file_tb $end
$scope module my_reg_file $end
$var reg 32 0 \REGISTERS[5] [31:0] $end
$upscope $end
$upscope $end
$scope module reg_file_tb $end
$scope module my_reg_file $end
$var reg 32 1 \REGISTERS[6] [31:0] $end
$upscope $end
$upscope $end
$scope module reg_file_tb $end
$scope module my_reg_file $end
$var reg 32 2 \REGISTERS[7] [31:0] $end
$upscope $end
$upscope $end
$scope module reg_file_tb $end
$scope module my_reg_file $end
$var reg 32 3 \REGISTERS[8] [31:0] $end
$upscope $end
$upscope $end
$scope module reg_file_tb $end
$scope module my_reg_file $end
$var reg 32 4 \REGISTERS[9] [31:0] $end
$upscope $end
$upscope $end
$scope module reg_file_tb $end
$scope module my_reg_file $end
$var reg 32 5 \REGISTERS[10] [31:0] $end
$upscope $end
$upscope $end
$scope module reg_file_tb $end
$scope module my_reg_file $end
$var reg 32 6 \REGISTERS[11] [31:0] $end
$upscope $end
$upscope $end
$scope module reg_file_tb $end
$scope module my_reg_file $end
$var reg 32 7 \REGISTERS[12] [31:0] $end
$upscope $end
$upscope $end
$scope module reg_file_tb $end
$scope module my_reg_file $end
$var reg 32 8 \REGISTERS[13] [31:0] $end
$upscope $end
$upscope $end
$scope module reg_file_tb $end
$scope module my_reg_file $end
$var reg 32 9 \REGISTERS[14] [31:0] $end
$upscope $end
$upscope $end
$scope module reg_file_tb $end
$scope module my_reg_file $end
$var reg 32 : \REGISTERS[15] [31:0] $end
$upscope $end
$upscope $end
$scope module reg_file_tb $end
$scope module my_reg_file $end
$var reg 32 ; \REGISTERS[16] [31:0] $end
$upscope $end
$upscope $end
$scope module reg_file_tb $end
$scope module my_reg_file $end
$var reg 32 < \REGISTERS[17] [31:0] $end
$upscope $end
$upscope $end
$scope module reg_file_tb $end
$scope module my_reg_file $end
$var reg 32 = \REGISTERS[18] [31:0] $end
$upscope $end
$upscope $end
$scope module reg_file_tb $end
$scope module my_reg_file $end
$var reg 32 > \REGISTERS[19] [31:0] $end
$upscope $end
$upscope $end
$scope module reg_file_tb $end
$scope module my_reg_file $end
$var reg 32 ? \REGISTERS[20] [31:0] $end
$upscope $end
$upscope $end
$scope module reg_file_tb $end
$scope module my_reg_file $end
$var reg 32 @ \REGISTERS[21] [31:0] $end
$upscope $end
$upscope $end
$scope module reg_file_tb $end
$scope module my_reg_file $end
$var reg 32 A \REGISTERS[22] [31:0] $end
$upscope $end
$upscope $end
$scope module reg_file_tb $end
$scope module my_reg_file $end
$var reg 32 B \REGISTERS[23] [31:0] $end
$upscope $end
$upscope $end
$scope module reg_file_tb $end
$scope module my_reg_file $end
$var reg 32 C \REGISTERS[24] [31:0] $end
$upscope $end
$upscope $end
$scope module reg_file_tb $end
$scope module my_reg_file $end
$var reg 32 D \REGISTERS[25] [31:0] $end
$upscope $end
$upscope $end
$scope module reg_file_tb $end
$scope module my_reg_file $end
$var reg 32 E \REGISTERS[26] [31:0] $end
$upscope $end
$upscope $end
$scope module reg_file_tb $end
$scope module my_reg_file $end
$var reg 32 F \REGISTERS[27] [31:0] $end
$upscope $end
$upscope $end
$scope module reg_file_tb $end
$scope module my_reg_file $end
$var reg 32 G \REGISTERS[28] [31:0] $end
$upscope $end
$upscope $end
$scope module reg_file_tb $end
$scope module my_reg_file $end
$var reg 32 H \REGISTERS[29] [31:0] $end
$upscope $end
$upscope $end
$scope module reg_file_tb $end
$scope module my_reg_file $end
$var reg 32 I \REGISTERS[30] [31:0] $end
$upscope $end
$upscope $end
$enddefinitions $end
#0
$dumpvars
bx I
bx H
bx G
bx F
bx E
bx D
bx C
bx B
bx A
bx @
bx ?
bx >
bx =
bx <
bx ;
bx :
bx 9
bx 8
bx 7
bx 6
bx 5
bx 4
bx 3
bx 2
bx 1
bx 0
bx /
bx .
bx -
bx ,
bx +
bx *
0)
1(
b1 '
bx &
b11 %
bx $
b0 #
b10 "
0!
$end
#10
b0 I
b0 H
b0 G
b0 F
b0 E
b0 D
b0 C
b0 B
b0 A
b0 @
b0 ?
b0 >
b0 =
b0 <
b0 ;
b0 :
b0 9
b0 8
b0 7
b0 6
b0 5
b0 4
b0 3
b0 2
b0 1
b0 0
b0 /
b0 .
b0 $
b0 -
b0 ,
b0 &
b0 +
b100000 *
1!
#20
0(
0!
#30
b10 +
1)
1!
#40
b10 %
0)
0!
#50
b10 '
b10 $
b0 %
1!
#60
b1 '
0!
#70
b0 I
b0 H
b0 G
b0 F
b0 E
b0 D
b0 C
b0 B
b0 A
b0 @
b0 ?
b0 >
b0 =
b0 <
b0 ;
b0 :
b0 9
b0 8
b0 7
b0 6
b0 5
b0 4
b0 3
b0 2
b0 1
b0 0
b0 /
b0 .
b0 -
b0 ,
b0 +
b0 $
b100000 *
b10 '
1(
1!
