code/cpu/alu_module/alu.v
// TODO : write testbench 

`timescale 1ns/100ps


module alu (DATA1, DATA2, RESULT, SELECT);

    input   [31:0]  DATA1, DATA2;
    input   [5:0]   SELECT; // 6bit allocated 5 bit mentioned in paper
    output  [31:0]  RESULT;

    reg     [31:0]  RESULT;

    // 18 operations mentioned
    wire    [31:0]  INTER_ADD,
                    INTER_SUB,
                    INTER_AND,
                    INTER_OR,
                    INTER_XOR,
                    INTER_SLT,
                    INTER_SLTU,
                    INTER_SLL,
                    INTER_SRL,
                    INTER_SRA,
                    INTER_MUL,
                    INTER_MULH,
                    INTER_MULHSU,
                    INTER_MULHU,
                    INTER_DIV,
                    INTER_REM,
                    INTER_REMU,
                    INTER_FWD; // intermediate to hold calculation

    // FLOAT not implemented


    //time delay set temp for operations
    assign INTER_FWD = DATA2;

    assign INTER_ADD = DATA1 + DATA2;
    assign INTER_SUB = DATA1 - DATA2;
    assign INTER_AND = DATA1 & DATA2;
    assign INTER_OR = DATA1 | DATA2;
    assign INTER_XOR = DATA1 ^ DATA2;

    // logical shift 
    assign  INTER_SLL = DATA1 << DATA2;
    assign  INTER_SRL = DATA1 >> DATA2;
    // arithmetic shift right
    assign  INTER_SRA = DATA1 >>> DATA2;

    assign  INTER_SLT = ($signed(DATA1) < $signed(DATA2)) ? 1'b1 : 1'b0 ; //set less than
    assign  INTER_SLTU = ($unsigned(DATA1) < $unsigned(DATA2)) ? 1'b1 : 1'b0; // set less than unsigned

    assign  INTER_MUL = DATA1 * DATA2; // multiplication
    // returns upper 32 bits of signed x unsigned  
    assign  INTER_MULHSU = $signed(DATA1) * $signed(DATA2); 
    // returns upper 32 bits of unsigned x unsigned  
    assign  INTER_MULHU = $unsigned(DATA1) * $unsigned(DATA2); // multiplication

    // signed integer division
    assign  INTER_DIV = $signed(DATA1) / $signed(DATA2);
    assign  INTER_REM = $signed(DATA1) % $signed(DATA2);

    // unsigned remainder
    assign  INTER_REMU = $unsigned(DATA1) % $unsigned(DATA2);

/*
ref: https://varshaaks.wordpress.com/2021/07/19/rv32i-base-integer-instruction-set/


R -Type

ADD, SUB , OR, XOR, AND
SLT, SLTU
SLL, SRL, SRA

I - Type

ADDI, ANDI, ORI, XORI
SLTI, (SLTUI)
SLLI, SRLI, SRAI


U -Type

LUI
AUIPC

J - Type

JALR
JAL

B - Type

BEQ BNEQ    
BLT BLTU
BGE BGEU

S - Type

LOAD LW LH LHU LB LBU
STORE SW SH SB 

*/

always @ (*)
begin
    case(SELECT)
        6'b000000:
            RESULT = INTER_ADD;
        6'b000001:
            RESULT = INTER_SLL;
        6'b000010:
            RESULT = INTER_SLT;
        6'b000011:
            RESULT = INTER_SLTU;

        6'b000100:
            RESULT = INTER_XOR;
        6'b000101:
            RESULT = INTER_SRL;
        6'b000110:
            RESULT = INTER_OR;
        6'b000111:
            RESULT = INTER_AND;

        // mul command
        6'b001000:
            RESULT = INTER_MUL;
        6'b001001:
            RESULT = INTER_MUL;
        6'b001010:
            RESULT = INTER_MULHSU;
        6'b001011:
            RESULT = INTER_MULHU;
        6'b001100:
            RESULT = INTER_DIV;
        6'b001101:
            RESULT = INTER_REM;
        6'b001111:
            RESULT = INTER_REMU;

        6'b010000:
            RESULT = INTER_SUB;
        6'b010101:
            RESULT = INTER_SRA;
        6'b011xxx:
            RESULT = INTER_FWD;
        default: RESULT = 0;
    endcase
end

endmodule

code/cpu/testbench/alu/alu_tb.v
`include "../../cpu/alu_module/alu.v"
`timescale 1ns/100ps

module alu_tb;

    // Declare connections to ALU
    reg[31:0] DATA1, DATA2;
    reg[5:0] SELECT;
    wire[31:0] RESULT;

    // Instantiate ALU module
    alu myALU(DATA1, DATA2, RESULT, SELECT);

    initial begin
        $dumpfile("alu_tb.vcd");
        $dumpvars(0,myALU);
    end

    initial begin
        DATA1 = 32'b00000000000000000000000000000010;
        DATA2 = 32'b00000000000000000000000000000011;
        SELECT = 6'b000000;
        #10;
        SELECT = 6'b000001;
        #10;
        SELECT = 6'b000010;
        #10;
        SELECT = 6'b000011;

        #10;
        SELECT = 6'b000100;
        #10;
        SELECT = 6'b000101;
        #10;
        SELECT = 6'b000110;
        #10;
        SELECT = 6'b000111;

        //mul commmand
        #10;
        SELECT = 6'b001000;
        #10;
        SELECT = 6'b001001;
        #10;
        SELECT = 6'b001010;
        #10;
        SELECT = 6'b001011;
        #10;
        SELECT = 6'b001100;
        #10;
        SELECT = 6'b001101;
        #10;
        SELECT = 6'b001111;


        #10;
        SELECT = 6'b010000;
        #10;
        SELECT = 6'b010101;
        #10;
        SELECT = 6'b011111;
        $finish;

    end

endmodule

code/cpu/testbench/alu/alu_tb.vcd
$date
	Thu Mar 16 14:22:23 2023
$end
$version
	Icarus Verilog
$end
$timescale
	100ps
$end
$scope module alu_tb $end
$scope module myALU $end
$var wire 32 ! DATA1 [31:0] $end
$var wire 32 " DATA2 [31:0] $end
$var wire 32 # INTER_AND [31:0] $end
$var wire 32 $ INTER_FWD [31:0] $end
$var wire 32 % INTER_OR [31:0] $end
$var wire 32 & INTER_XOR [31:0] $end
$var wire 6 ' SELECT [5:0] $end
$var wire 32 ( INTER_SUB [31:0] $end
$var wire 32 ) INTER_SRL [31:0] $end
$var wire 32 * INTER_SRA [31:0] $end
$var wire 32 + INTER_SLTU [31:0] $end
$var wire 32 , INTER_SLT [31:0] $end
$var wire 32 - INTER_SLL [31:0] $end
$var wire 32 . INTER_REMU [31:0] $end
$var wire 32 / INTER_REM [31:0] $end
$var wire 32 0 INTER_MULHU [31:0] $end
$var wire 32 1 INTER_MULHSU [31:0] $end
$var wire 32 2 INTER_MUL [31:0] $end
$var wire 32 3 INTER_DIV [31:0] $end
$var wire 32 4 INTER_ADD [31:0] $end
$var reg 32 5 RESULT [31:0] $end
$upscope $end
$upscope $end
$enddefinitions $end
#0
$dumpvars
b101 5
b101 4
b0 3
b110 2
b110 1
b110 0
b10 /
b10 .
b10000 -
b1 ,
b1 +
b0 *
b0 )
b11111111111111111111111111111111 (
b0 '
b1 &
b11 %
b11 $
b10 #
b11 "
b10 !
$end
#100
b10000 5
b1 '
#200
b1 5
b10 '
#300
b11 '
#400
b100 '
#500
b0 5
b101 '
#600
b11 5
b110 '
#700
b10 5
b111 '
#800
b110 5
b1000 '
#900
b1001 '
#1000
b1010 '
#1100
b1011 '
#1200
b0 5
b1100 '
#1300
b10 5
b1101 '
#1400
b1111 '
#1500
b11111111111111111111111111111111 5
b10000 '
#1600
b0 5
b10101 '
#1700
b11111 '
